slab/__init__.py
slab/binaural.py
slab/filter.py
slab/hrtf.py
slab/psychoacoustics.py
slab/signal.py
slab/sound.py
slab/data/mit_kemar_ils.pkl
slab/data/mit_kemar_normal_pinna.bz2
slab/experiments/__init__.py
slab/experiments/motion_speed.py
slab/experiments/room_voice_interference.py
slab-1.8.2.dist-info/licenses/LICENSE
slab-1.8.2.dist-info/METADATA
slab-1.8.2.dist-info/WHEEL
slab-1.8.2.dist-info/top_level.txt
slab-1.8.2.dist-info/RECORD
