Metadata-Version: 2.4
Name: slab
Version: 1.8.2
Summary: Tools for generating and manipulating digital signals, particularly sounds.
Home-page: http://github.com/DrMarc/slab.git
Author: Marc Schoenwiesner
Author-email: marc.schoenwiesner@gmail.com
License: MIT
Requires-Python: >=3.6
License-File: LICENSE
Requires-Dist: numpy
Requires-Dist: scipy
Requires-Dist: SoundFile
Requires-Dist: SoundDevice
Requires-Dist: matplotlib<3.4; python_version == "3.6"
Requires-Dist: matplotlib; python_version >= "3.7"
Provides-Extra: testing
Requires-Dist: pytest; extra == "testing"
Requires-Dist: h5netcdf; extra == "testing"
Provides-Extra: docs
Requires-Dist: sphinx; extra == "docs"
Requires-Dist: sphinx-rtd-theme; extra == "docs"
Provides-Extra: hrtf
Requires-Dist: h5netcdf; extra == "hrtf"
Dynamic: author
Dynamic: author-email
Dynamic: description
Dynamic: description-content-type
Dynamic: home-page
Dynamic: license
Dynamic: license-file
Dynamic: provides-extra
Dynamic: requires-dist
Dynamic: requires-python
Dynamic: summary
